Workbook

Sheet BOM colonnina
A1: Bill of Materials - retrofit smart di UNA colonnina (2 prese elettriche + 2 idriche)
A2: Idraulica gia' funzionante: in questo BOM solo la parte elettrica smart. Link per quantita' pilota (~5 kit).
A4: # | B4: Componente | C4: Modello consigliato | D4: Q.ta' | E4: Prezzo unit. (EUR) | F4: Totale (EUR) | G4: Link acquisto
A5: 1 | B5: ESP32 WiFi con antenna ESTERNA | C5: ESP32-WROOM-32U DevKit DUBEUYEW (kit 3 pz, antenna + pigtail inclusi) | D5: 1 | E5: 7.69 | F5: =D5*E5 -> 7.69 | G5: Aliexpress | H5: -
A6: 2 | B6: Antenna WiFi 2.4 GHz IP67 (upgrade outdoor opzionale) | C6: omnidirezionale 7 dBi IP67 SMA, range 700-6000 MHz | D6: 1 | E6: 11.49 | F6: =D6*E6 -> 11.49 | G6: Aliexpress | H6: -
A7: 3 | B7: Misuratore energia + TA | C7: PZEM-004T v3 + TA 100A toroidale split-core | D7: 2 | E7: 10 | F7: =D7*E7 -> 20 | G7: Aliexpress | H7: -
A8: 4 | B8: Contattore 25A 2NO bobina 12 V DC | C8: Finder 22.32.0.012.4320 (2NO, 12 V AC/DC) | D8: 2 | E8: 20 | F8: =D8*E8 -> 40 | G8: Amazon | H8: - ?
A9: 5 | B9: Driver MOSFET per bobina 12 V (logic-level) | C9: IRLZ44N TO-220AB (kit 5 pz) + diodo 1N4007 flyback (R 220Ohm dal kit resistori) | D9: 2 | E9: 2 | F9: =D9*E9 -> 4 | G9: Amazon (15 pz) | H9: -
A10: 6 | B10: Alimentatore AC/DC 12 V (bobine + buck logica) | C10: HiLink HLK-10M12 (12 V 10 W, 833 mA) - kit 2 pz - upgrade da HLK-PM12 sottodim. | D10: 1 | E10: 11 | F10: =D10*E10 -> 11 | G10: Amazon (kit 2 pz)
A11: 7 | B11: Buck step-down 12 V -> 5 V per ESP32+PZEM | C11: MP1584EN regolabile (kit 6 pz) | D11: 1 | E11: 2 | F11: =D11*E11 -> 2 | G11: Amazon (6 pz)
A12: 8 | B12: LED stato RGB | C12: Aihasd WS2812B 12-LED anello | D12: 1 | E12: 2 | F12: =D12*E12 -> 2 | G12: Amazon
A13: 9 | B13: Sticker QR custom resistente UV/salino | C13: stampa adesivi vinile o alluminio personalizzati | D13: 2 | E13: 1 | F13: =D13*E13 -> 2 | G13: VistaPrint
A14: 10 | B14: Pulsante emergenza fungo NC 22 mm IP66 | C14: Push button rosso 1NO+1NC IP66 con cassetta | D14: 1 | E14: 8 | F14: =D14*E14 -> 8 | G14: Amazon
A15: 11 | B15: Morsettiera + DIN rail + accessori | C15: HERKINDNESS kit DIN 35 mm con morsetti UK-2.5B | D15: 1 | E15: 8 | F15: =D15*E15 -> 8 | G15: Amazon
A16: 12 | B16: Cavo 2,5 mm2 + fascette + cassetta interna IP66 (294x152x75 mm, dissipazione passiva) | C16: Cavo H07V-K 100 m + cassetta Gewiss IP66 grande GW48007 | D16: 1 | E16: 12 | F16: =D16*E16 -> 12 | G16: Amazon (cassetta)
A17: 14 | B17: Sensore temperatura DS18B20 waterproof (monitor + auto-protezione firmware) | C17: AZDelivery sonda INOX 1 m (kit 2 pz) | D17: 1 | E17: 3 | F17: =D17*E17 -> 3 | G17: Aliexpress | H17: -
A18: 15 | B18: Kit pressacavi IP68 (per ingressi cavi cassetta IP66) | C18: ARPDJK 32 pz misto M12/M16/M20/M25 - 3-15 mm | D18: 1 | E18: 10 | F18: =D18*E18 -> 10 | G18: Amazon (kit 32 pz)
A19: 16 | B19: Kit resistori 1/4 W (4,7 kOhm pull-up DS18B20, 220 Ohm gate MOSFET, scorta) | C19: BOJACK assortimento 1000 pz, 25 valori, 5% | D19: 1 | E19: 9 | F19: =D19*E19 -> 9 | G19: Amazon (1000 pz)
B20: TOTALE materiali per colonnina | F20: =SUM(F5:F19) -> 150.18
A22: Note:
B23: - Differenziale 30 mA, magnetotermici e cablaggi 230 V sono presenti nelle colonnine esistenti.
B24: - Manodopera elettricista non in BOM: gestita separatamente / interna.
B25: - L'antenna riga 2 e' un upgrade outdoor IP67. Il kit DUBEUYEW (riga 1) include gia' una antenna 3 dBi + pigtail IPEX-SMA.
B26: - ESP32-U + antenna esterna risolvono la schermatura WiFi della cassetta metallica della colonnina.
B27: - Contattore con bobina 12 V DC + driver MOSFET = piu' affidabile e con meno componenti del modulo rele' + contattore 230 V AC.
B28: - MOSFET IRLZ44N dissipa <1 mW pilotando la bobina (180 mA): NON serve dissipatore.
B29: - Sfiato membrana + cassetta 294x152x75 + DS18B20 firmware = gestione termica cassetta sotto sole siciliano.
B30: - Alimentatore HLK-10M12 (10W) dimensionato per: 2x bobine contattore (~4,4W) + buck 5V per ESP32+PZEM+LED (~2W) + margine inrush.
B31: - Pressacavi obbligatori su tutti gli ingressi cavi della cassetta IP66: senza, l'IP grade reale crolla a IP20.
B32: - Resistore 4,7 kOhm tra DATA e VCC del DS18B20: senza pull-up il bus OneWire non funziona.
B33: - Per fatturazione kWh certificata MID: sostituire PZEM con Eastron SDM230-MID (+~40 EUR/colonnina).
B34: - I link sono ad oggi 14/05/2026: verificare prezzo e disponibilita' prima dell'ordine.

Sheet Infrastruttura molo
A1: Infrastruttura di molo - rete 100% wireless (mesh outdoor)
A2: Nessun cablaggio tra access point: copertura mesh WiFi 6, ogni nodo alimentato in 220 V locale.
A4: # | B4: Voce | C4: Modello | D4: Q.ta' | E4: Prezzo (EUR) | F4: Link acquisto
A5: 1 | B5: Router LTE industriale (gateway internet) | C5: Teltonika RUT240 EU Standard | D5: 1 | E5: 250 | F5: Amazon
A6: 2 | B6: SIM dati M2M 5 GB/anno | C6: Vodafone Business M2M / 1NCE (contratto annuale) | D6: 1 | E6: 60 | F6: Vodafone Business
A7: 3 | B7: Mesh AP outdoor WiFi 6 AX3000 IP65 | C7: TP-Link Deco X50-Outdoor | D7: 3 | E7: 150 | F7: Amazon
A8: 4 | B8: Broker MQTT locale + cache offline | C8: Raspberry Pi 4 4 GB Starter Kit (case + alim. + SD 64 GB) | D8: 1 | E8: 90 | F8: Amazon
A9: 5 | B9: Cassetta tecnica IP66 grande | C9: Gewiss GW48007 294x152x75 mm IP66 con guida DIN | D9: 1 | E9: 60 | F9: Amazon
A10: 6 | B10: UPS 12 V autonomia ~4 h (per router + Pi) | C10: Alphaelettronica KUPSM010 mini-UPS 10000 mAh | D10: 1 | E10: 40 | F10: Amazon
A11: 7 | B11: Pali / staffe outdoor per Deco (se servono) | C11: supporti palo universali per AP | D11: 3 | E11: 25 | F11: Amazon (ricerca)
B12: Subtotale infrastruttura | E12: =SUMPRODUCT(D5:D11,E5:E11) -> 1025
A14: Note:
B15: - Deco X50-Outdoor: WiFi 6 AX3000, IP65, range outdoor fino a 70 m; un nodo cablato al router, gli altri in mesh.
B16: - Coprire 80 colonnine su un molo di ~150 m richiede tipicamente 2-3 nodi a seconda dell'ostruzione.
B17: - Il Raspberry Pi sta nella cassetta tecnica con il router e fa da broker MQTT locale + cache offline.
B18: - Tutte le colonnine si collegano al WiFi mesh; non serve cablare un cavo dati a ogni colonnina.
B19: - Il piano SIM Vodafone Business M2M e' un esempio: confronta con 1NCE, ThingsMobile o altri provider M2M.

Sheet Riepilogo budget
A1: Riepilogo budget - Nautica GLEM colonnine smart
A3: Parametri (celle blu = modificabili)
A4: Numero colonnine | B4: 50
A5: Costo materiali per colonnina (EUR) | B5: ='BOM colonnina'!F20 -> 150.18
A6: Costo infrastruttura totale (EUR) | B6: ='Infrastruttura molo'!E12 -> 1025
A7: Sviluppo software (EUR) | B7: 21000
A8: Setup VPS + dominio + grafica + collaudi (EUR) | B8: 500
A10: CAPEX - Investimento iniziale
A11: Hardware colonnine (n. unita x prezzo) | B11: =B4*B5 -> 7509
A12: Infrastruttura di molo | B12: =B6 -> 1025
A13: Sviluppo software | B13: =B7 -> 21000
A14: Setup vari | B14: =B8 -> 500
A15: TOTALE CAPEX | B15: =SUM(B11:B14) -> 30034
A17: OPEX mensile
A18: VPS Hetzner CX31 | B18: 13
A19: Backup Storage Box | B19: 4
A20: SIM dati M2M | B20: 5
A21: Manutenzione hardware (forfait) | B21: 50
A22: TOTALE OPEX/mese | B22: =SUM(B18:B21) -> 72
A23: (+) Stripe ~3% sulle ricariche - variabile
A26: Ricavi attesi (modello semplice)
A27: kWh medi per presa/mese (mix anno) | B27: 30
A28: Prese per colonnina | B28: 2
A29: Tariffa applicata (EUR/kWh) | B29: 0.55
A30: Costo energia (EUR/kWh) | B30: 0.3
A32: kWh erogati/mese | B32: =B4*B28*B27 -> 3000
A33: Ricavi lordi/mese | B33: =B32*B29 -> 1650
A34: Costo energia/mese | B34: =B32*B30 -> 900
A35: Margine energia/mese | B35: =B33-B34 -> 750
A36: OPEX/mese (da sopra) | B36: =B22 -> 72
A37: Utile lordo mensile | B37: =B35-B36 -> 678
A38: Utile lordo annuo | B38: =B37*12 -> 8136
A40: Payback (mesi) - hardware+infra+setup | B40: =IFERROR((B11+B12+B14)/B37,"-") -> 13.324484
A41: Payback (mesi) - investimento completo | B41: =IFERROR(B15/B37,"-") -> 44.297935

Sheet Sensitivity
A1: Sensitivity sul numero di colonnine
A3: N. colonnine | B3: CAPEX hw+infra+setup | C3: CAPEX totale (incl. SW) | D3: Ricavi mensili lordi | E3: Utile mensile | F3: Payback completo (mesi)
A4: 20 | B4: =A4*'BOM colonnina'!F20+'Infrastruttura molo'!E12+'Riepilogo budget'!B8 -> 4528.6 | C4: =B4+'Riepilogo budget'!B7 -> 25528.6 | D4: =A4*'Riepilogo budget'!B28*'Riepilogo budget'!B27*'Riepilogo budget'!B29 -> 660 | E4: =A4*'Riepilogo budget'!B28*'Riepilogo budget'!B27*('Riepilogo budget'!B29-'Riepilogo budget'!B30)-'Riepilogo budget'!B22 -> 228 | F4: =IFERROR(C4/E4,"-") -> 111.96754
A5: 30 | B5: =A5*'BOM colonnina'!F20+'Infrastruttura molo'!E12+'Riepilogo budget'!B8 -> 6030.4 | C5: =B5+'Riepilogo budget'!B7 -> 27030.4 | D5: =A5*'Riepilogo budget'!B28*'Riepilogo budget'!B27*'Riepilogo budget'!B29 -> 990 | E5: =A5*'Riepilogo budget'!B28*'Riepilogo budget'!B27*('Riepilogo budget'!B29-'Riepilogo budget'!B30)-'Riepilogo budget'!B22 -> 378 | F5: =IFERROR(C5/E5,"-") -> 71.508995
A6: 50 | B6: =A6*'BOM colonnina'!F20+'Infrastruttura molo'!E12+'Riepilogo budget'!B8 -> 9034 | C6: =B6+'Riepilogo budget'!B7 -> 30034 | D6: =A6*'Riepilogo budget'!B28*'Riepilogo budget'!B27*'Riepilogo budget'!B29 -> 1650 | E6: =A6*'Riepilogo budget'!B28*'Riepilogo budget'!B27*('Riepilogo budget'!B29-'Riepilogo budget'!B30)-'Riepilogo budget'!B22 -> 678 | F6: =IFERROR(C6/E6,"-") -> 44.297935
A7: 80 | B7: =A7*'BOM colonnina'!F20+'Infrastruttura molo'!E12+'Riepilogo budget'!B8 -> 13539.4 | C7: =B7+'Riepilogo budget'!B7 -> 34539.4 | D7: =A7*'Riepilogo budget'!B28*'Riepilogo budget'!B27*'Riepilogo budget'!B29 -> 2640 | E7: =A7*'Riepilogo budget'!B28*'Riepilogo budget'!B27*('Riepilogo budget'!B29-'Riepilogo budget'!B30)-'Riepilogo budget'!B22 -> 1128 | F7: =IFERROR(C7/E7,"-") -> 30.620035
A8: 100 | B8: =A8*'BOM colonnina'!F20+'Infrastruttura molo'!E12+'Riepilogo budget'!B8 -> 16543 | C8: =B8+'Riepilogo budget'!B7 -> 37543 | D8: =A8*'Riepilogo budget'!B28*'Riepilogo budget'!B27*'Riepilogo budget'!B29 -> 3300 | E8: =A8*'Riepilogo budget'!B28*'Riepilogo budget'!B27*('Riepilogo budget'!B29-'Riepilogo budget'!B30)-'Riepilogo budget'!B22 -> 1428 | F8: =IFERROR(C8/E8,"-") -> 26.290616

Sheet Note
A1: Note, fonti e changelog
A3: v2.3 (14/05/2026, correzioni gap di revisione ingegneria):
A4: - HLK-PM12 (3W) -> HLK-10M12 (10W): l'alimentatore precedente era sottodimensionato.
A5: - Aggiunto kit pressacavi IP68: senza, la cassetta IP66 perde la classificazione.
A6: - Aggiunto kit resistori (4,7 kOhm pull-up DS18B20 obbligatoria + 220 Ohm gate MOSFET).
A8: v2.2 (14/05/2026, gestione termica):
A9: - Aggiunto sfiato a membrana M12 IP69 (RS) per ventilazione passiva contro il caldo siciliano.
A10: - Aggiunto sensore temperatura DS18B20 waterproof - monitor cassetta e auto-protezione firmware.
A11: - Cassetta interna passata da 196x152 a 294x152 mm per maggior dissipazione passiva.
A12: - Conferma: il MOSFET IRLZ44N NON necessita di dissipatore (dissipa <1 mW).
A14: v2.1 (link acquisto):
A15: - Aggiunta colonna Link acquisto in BOM colonnina e Infrastruttura molo.
... A33: - BLU = input modificabile, NERO = formula, sfondo GIALLO = assunzione chiave, link = AZZURRO sottolineato.
